opensimplex/__init__.py
opensimplex/api.py
opensimplex/constants.py
opensimplex/internals.py
tests/__init__.py
tests/benchmark_opensimplex.py
tests/numpy_shapes.npz
tests/samples.json.gz
tests/test_opensimplex.py
opensimplex-0.4.5.1.dist-info/LICENSE
opensimplex-0.4.5.1.dist-info/METADATA
opensimplex-0.4.5.1.dist-info/WHEEL
opensimplex-0.4.5.1.dist-info/top_level.txt
opensimplex-0.4.5.1.dist-info/RECORD
