Metadata-Version: 2.1
Name: opensimplex
Version: 0.4.5.1
Summary: OpenSimplex is a noise generation function like Perlin or Simplex noise, but better.
Home-page: https://code.larus.se/lmas/opensimplex
Download-URL: https://code.larus.se/lmas/opensimplex/releases
Author: Alex
Author-email: opensimplex@larus.se
License: MIT
Keywords: opensimplex simplex noise 2D 3D 4D
Classifier: Programming Language :: Python :: 3
Classifier: License :: OSI Approved :: MIT License
Classifier: Operating System :: OS Independent
Classifier: Topic :: Scientific/Engineering :: Mathematics
Requires-Python: >=3.8
License-File: LICENSE
